setup.py
curator/__init__.py
curator/curator.py
curator/loader.py
curator/script.py
curator/tests/__init__.py
curator/tests/test_load_scripts.py
redis_lua_curator.egg-info/PKG-INFO
redis_lua_curator.egg-info/SOURCES.txt
redis_lua_curator.egg-info/dependency_links.txt
redis_lua_curator.egg-info/requires.txt
redis_lua_curator.egg-info/top_level.txt