Metadata-Version: 1.1
Name: redis-lua-curator
Version: 0.3.0
Summary: Helper for working with lua scripts.
Home-page: https://github.com/mhahn/curator/
Author: Michael Hahn
Author-email: mwhahn@gmail.com
License: UNKNOWN
Download-URL: https://github.com/mhahn/curator/tarball/0.3.0
Keywords: redis,lua
Platform: UNKNOWN
